yacrs/__init__.py
yacrs/config.py
yacrs/version.py
yacrs-0.0.1.dist-info/METADATA
yacrs-0.0.1.dist-info/WHEEL
yacrs-0.0.1.dist-info/top_level.txt
yacrs-0.0.1.dist-info/RECORD
