Metadata-Version: 2.2
Name: yacrs
Version: 0.0.1
Summary: Yet Anothor Configuration and Registration System
Home-page: https://github.com/Cowhisper/yacrs
Author: Cowhisper
Author-email: niu1187203155@gmail.com
Classifier: Programming Language :: Python :: 3
Classifier: License :: OSI Approved :: MIT License
Classifier: Operating System :: OS Independent
Requires-Python: >=3.8
Dynamic: author
Dynamic: author-email
Dynamic: classifier
Dynamic: description
Dynamic: description-content-type
Dynamic: home-page
Dynamic: requires-python
Dynamic: summary
